rockset/__init__.py
rockset/alias.py
rockset/client.py
rockset/clustering_key.py
rockset/collection.py
rockset/credentials.py
rockset/cursor.py
rockset/document.py
rockset/document_locator_pb2.py
rockset/document_locator_pb2_grpc.py
rockset/document_pb2.py
rockset/document_pb2_grpc.py
rockset/exception.py
rockset/field_mapping.py
rockset/integration.py
rockset/query.py
rockset/query_field_path_pb2.py
rockset/query_field_path_pb2_grpc.py
rockset/query_lambda.py
rockset/regex_pb2.py
rockset/regex_pb2_grpc.py
rockset/resource.py
rockset/source.py
rockset/unittest.py
rockset/value.py
rockset/value_pb2.py
rockset/value_pb2_grpc.py
rockset/version.json
rockset/workspace.py
rockset/rock/__init__.py
rockset/rock/main.py
rockset/rock/commands/__init__.py
rockset/rock/commands/command.py
rockset/rock/commands/command_auth.py
rockset/rock/commands/command_rest.py
rockset/rock/commands/configure.py
rockset/rock/commands/create.py
rockset/rock/commands/describe.py
rockset/rock/commands/drop.py
rockset/rock/commands/get.py
rockset/rock/commands/list.py
rockset/rock/commands/play.py
rockset/rock/commands/remove.py
rockset/rock/commands/setstate.py
rockset/rock/commands/sqlquery.py
rockset/rock/commands/upload.py
rockset/rock/commands/util/__init__.py
rockset/rock/commands/util/parse_util.py
rockset/rock/commands/util/type_util.py
rockset/sql/__init__.py
rockset/sql/dbapi.py
rockset/sql/exception.py
rockset/sql/sqlalchemy.py
rockset/swagger_client/__init__.py
rockset/swagger_client/api_client.py
rockset/swagger_client/configuration.py
rockset/swagger_client/rest.py
rockset/swagger_client/api/__init__.py
rockset/swagger_client/api/aliases_api.py
rockset/swagger_client/api/api_keys_api.py
rockset/swagger_client/api/collections_api.py
rockset/swagger_client/api/custom_roles_api.py
rockset/swagger_client/api/documents_api.py
rockset/swagger_client/api/integrations_api.py
rockset/swagger_client/api/organizations_api.py
rockset_sqlcli-0.8.10.dist-info/DESCRIPTION.rst
rockset_sqlcli-0.8.10.dist-info/METADATA
rockset_sqlcli-0.8.10.dist-info/RECORD
rockset_sqlcli-0.8.10.dist-info/WHEEL
rockset_sqlcli-0.8.10.dist-info/entry_points.txt
rockset_sqlcli-0.8.10.dist-info/metadata.json
rockset_sqlcli-0.8.10.dist-info/top_level.txt
