Metadata-Version: 2.0
Name: rockset-sqlcli
Version: 0.8.10
Summary: Rockset SQL REPL for `rock sql`
Home-page: https://rockset.com
Author: Rockset, Inc
Author-email: api@rockset.io
License: UNKNOWN
Keywords: Rockset serverless search and analytics
Platform: UNKNOWN
Classifier: License :: OSI Approved :: BSD License
Classifier: Development Status :: 4 - Beta
Classifier: Environment :: Console
Classifier: Environment :: Other Environment
Classifier: Intended Audience :: Developers
Classifier: Intended Audience :: Information Technology
Classifier: Intended Audience :: Science/Research
Classifier: Operating System :: OS Independent
Classifier: Programming Language :: Python :: 3.5
Classifier: Programming Language :: Python :: 3.6
Classifier: Programming Language :: Python :: 3.7
Classifier: Programming Language :: SQL
Classifier: Topic :: Database
Classifier: Topic :: Database :: Database Engines/Servers
Classifier: Topic :: Scientific/Engineering :: Information Analysis
Classifier: Topic :: Software Development
Classifier: Topic :: Software Development :: Libraries
Classifier: Topic :: Software Development :: Libraries :: Application Frameworks
Classifier: Topic :: Software Development :: Libraries :: Python Modules
Classifier: Topic :: System :: Shells
Classifier: Topic :: Internet :: WWW/HTTP :: Indexing/Search
Requires-Dist: cli-helpers[styles] (>=1.0.1)
Requires-Dist: click (>=4.1)
Requires-Dist: configobj (>=5.0.6)
Requires-Dist: humanize (>=0.5.1)
Requires-Dist: prompt-toolkit (==1.0.13)
Requires-Dist: Pygments (>=2.0)
Requires-Dist: pyyaml (>=3.11)
Requires-Dist: rockset (>=0.6.0b20190617)
Requires-Dist: sqlparse (>=0.2.2)
Requires-Dist: webcolors (>=1.7)
